{
    "$schema": "../../schemas/feature.schema.json",
    "id": "021-feature-ecological_construction",
    "name": {
        "es": "Construcción ecológica",
        "en": "Construcción ecológica",
        "pt": "Construcción ecológica"
    },
    "slug": "ecological_construction",
    "description": {
        "es": "Edificación sustentable con materiales ecológicos, técnicas de bioconstrucción y mínimo impacto ambiental",
        "en": "Edificación sustentable con materiales ecológicos, técnicas de bioconstrucción y mínimo impacto ambiental",
        "pt": "Edificación sustentable con materiales ecológicos, técnicas de bioconstrucción y mínimo impacto ambiental"
    },
    "icon": "EcoConstructionIcon",
    "isBuiltin": true,
    "isFeatured": false,
    "displayWeight": 35,
    "lifecycleState": "ACTIVE"
}
