{
    "$schema": "../../schemas/feature.schema.json",
    "id": "053-feature-digital_detox_zone",
    "slug": "digital_detox_zone",
    "description": {
        "es": "Área libre de dispositivos electrónicos y señales digitales para desconexión total y relajación",
        "en": "Área libre de dispositivos electrónicos y señales digitales para desconexión total y relajación",
        "pt": "Área libre de dispositivos electrónicos y señales digitales para desconexión total y relajación"
    },
    "applicableVerticals": ["accommodation"],
    "icon": "DigitalDetoxIcon",
    "isBuiltin": true,
    "isFeatured": false,
    "displayWeight": 25,
    "lifecycleState": "ACTIVE"
}
