{
    "$schema": "../../schemas/amenity.schema.json",
    "id": "029-amenity-outdoors-private-garden",
    "name": {
        "es": "private_garden",
        "en": "private_garden",
        "pt": "private_garden"
    },
    "slug": "private_garden",
    "description": {
        "es": "Jardín privado",
        "en": "Jardín privado",
        "pt": "Jardín privado"
    },
    "type": "OUTDOORS",
    "icon": "PrivateGardenIcon",
    "isBuiltin": false,
    "isFeatured": true,
    "displayWeight": 48
}
