{
    "id": "review-029-chajari-laura_editor",
    "userId": "f47ac10b-58cc-4372-a567-0e02b2c3d487",
    "destinationId": "chajari",
    "title": "Perfecto para turismo de naturaleza",
    "content": "Si buscas conectar con la naturaleza, este es tu Chajarí. Los paisajes son espectaculares, hay muchas actividades al aire libre y el ambiente es muy tranquilo. Ideal para fotografía y senderismo.",
    "rating": {
        "landscape": 5,
        "attractions": 5,
        "accessibility": 3,
        "safety": 5,
        "cleanliness": 4,
        "hospitality": 4,
        "culturalOffer": 3,
        "gastronomy": 5,
        "affordability": 5,
        "nightlife": 2,
        "infrastructure": 3,
        "environmentalCare": 4,
        "wifiAvailability": 2,
        "shopping": 1,
        "beaches": 4,
        "greenSpaces": 5,
        "localEvents": 4,
        "weatherSatisfaction": 5
    }
}