{
    "slug": "teatro_italia",
    "lat": -33.1478387,
    "long": -59.3152772,
    "type": "OTHER",
    "icon": null,
    "description": "Teatro histórico y centro artístico-cultural de la ciudad, utilizado para obras, música, talleres y presentaciones.",
    "nameI18n": {
        "es": "Teatro Italia",
        "en": null,
        "pt": null
    },
    "descriptionI18n": {
        "es": "Teatro histórico y centro artístico-cultural de la ciudad, utilizado para obras, música, talleres y presentaciones.",
        "en": null,
        "pt": null
    },
    "translationMeta": {},
    "address": "Islas Malvinas entre Bartolomé Mitre y Rivadavia, Gualeguay, Entre Ríos",
    "keywords": [
        "teatro italia gualeguay",
        "teatro historico",
        "islas malvinas",
        "artes escenicas",
        "cultura"
    ],
    "hasOwnPage": false,
    "isBuiltin": true,
    "isFeatured": true,
    "displayWeight": 100,
    "verified": false,
    "verifiedAt": null,
    "source": "https://www.entrerios.tur.ar/localidades-1/gualeguay; https://gualeguay.jimdofree.com/puerto-ruiz/mas-lugares-interesantes/",
    "notes": "Nombre, función y ubicación general confirmados. Falta geocodificar el acceso o punto representativo. Coordinates auto-geocoded from address on 2026-07-13 via google-places; pending human cartographic verification.",
    "lifecycleState": "ACTIVE",
    "categories": [
        {
            "slug": "theater",
            "isPrimary": true
        },
        {
            "slug": "historic_site",
            "isPrimary": false
        },
        {
            "slug": "architecture",
            "isPrimary": false
        },
        {
            "slug": "entertainment",
            "isPrimary": false
        }
    ]
}
