{
    "$schema": "../../../schemas/accommodationReview.schema.json",
    "id": "review-032-sueno-natural-apartment-federacion-moderator",
    "userId": "moderator-user-67890",
    "accommodationId": "sueno-natural-apartment-federacion",
    "title": "Perfecto para descansar",
    "content": "Exactamente lo que necesitaba. Un lugar tranquilo, limpio y cómodo. La atención personalizada hace la diferencia. Las instalaciones están bien mantenidas y el ambiente es muy relajante.",
    "rating": {
        "cleanliness": 5,
        "hospitality": 4,
        "services": 4,
        "accuracy": 5,
        "communication": 5,
        "location": 4
    },
    "lifecycleState": "ACTIVE"
}