{
    "$schema": "../../schemas/point-of-interest.schema.json",
    "id": "810-point-of-interest-san_justo_comisaria",
    "slug": "san_justo_comisaria",
    "lat": -32.445012,
    "long": -58.4405631,
    "type": "OTHER",
    "icon": null,
    "description": "Dependencia policial de referencia para seguridad pública y emergencias.",
    "nameI18n": {
        "es": "Comisaría de San Justo",
        "en": null,
        "pt": null
    },
    "descriptionI18n": {
        "es": "Dependencia policial de referencia para seguridad pública y emergencias.",
        "en": null,
        "pt": null
    },
    "translationMeta": {},
    "address": "San Justo, Entre Ríos",
    "keywords": ["comisaria san justo", "policia", "seguridad", "emergencias", "servicios"],
    "hasOwnPage": false,
    "isBuiltin": true,
    "isFeatured": true,
    "displayWeight": 100,
    "verified": false,
    "verifiedAt": null,
    "source": "https://www.facebook.com/municipalidadsanjustoentrerios/; https://mapcarta.com/es/19203230",
    "notes": "Nombre, función y ubicación general confirmados. Falta geocodificar el acceso o punto representativo. Coordinates auto-geocoded from address on 2026-07-13 via google-places; pending human cartographic verification.",
    "lifecycleState": "ACTIVE",
    "categories": [
        {
            "slug": "government",
            "isPrimary": true
        },
        {
            "slug": "services",
            "isPrimary": false
        }
    ]
}
